types/__init__.py
types/base.py
types/entity.py
types/events.py
types/payload.py
types/timestamp.py
dlist_top-0.1.1.dist-info/LICENSE
dlist_top-0.1.1.dist-info/METADATA
dlist_top-0.1.1.dist-info/WHEEL
dlist_top-0.1.1.dist-info/top_level.txt
dlist_top-0.1.1.dist-info/RECORD
