Metadata-Version: 2.1
Name: dlist-top
Version: 0.1.1
Summary: DList.top client for Python
Home-page: https://github.com/dlist-top/client-py
Author: DList.top
License: MIT License        
Platform: UNKNOWN
Requires-Python: >=3.8
License-File: LICENSE
